infi.pyvmomi_wrapper-0.1.29-py2.7-nspkg.pth
infi/pyvmomi_wrapper/__init__.py
infi/pyvmomi_wrapper/__version__.py
infi/pyvmomi_wrapper/client.py
infi/pyvmomi_wrapper/connect.py
infi/pyvmomi_wrapper/errors.py
infi/pyvmomi_wrapper/extension.py
infi/pyvmomi_wrapper/format_object.py
infi/pyvmomi_wrapper/property_collector.py
infi/pyvmomi_wrapper/resources.py
infi/pyvmomi_wrapper/tasks.py
infi/pyvmomi_wrapper/esxcli/MoreTypes.py
infi/pyvmomi_wrapper/esxcli/ReflectTypes.py
infi/pyvmomi_wrapper/esxcli/__init__.py
infi/pyvmomi_wrapper/esxcli/cli.py
infi/pyvmomi_wrapper/sms/__init__.py
infi/pyvmomi_wrapper/sms/client.py
infi.pyvmomi_wrapper-0.1.29.dist-info/LICENSE
infi.pyvmomi_wrapper-0.1.29.dist-info/METADATA
infi.pyvmomi_wrapper-0.1.29.dist-info/WHEEL
infi.pyvmomi_wrapper-0.1.29.dist-info/entry_points.txt
infi.pyvmomi_wrapper-0.1.29.dist-info/namespace_packages.txt
infi.pyvmomi_wrapper-0.1.29.dist-info/top_level.txt
infi.pyvmomi_wrapper-0.1.29.dist-info/RECORD
