Metadata-Version: 2.1
Name: infi.pyvmomi-wrapper
Version: 0.1.29
Summary: Wrapper for pyvmomi
Home-page: https://github.com/Infinidat/infi.pyvmomi_wrapper
Author: Arnon Yaari
Author-email: arnony@infinidat.com
License: BSD
Platform: UNKNOWN
Classifier: Intended Audience :: Developers
Classifier: Intended Audience :: System Administrators
Classifier: License :: OSI Approved :: BSD License
Classifier: Operating System :: OS Independent
Classifier: Programming Language :: Python
Classifier: Programming Language :: Python :: 2
Classifier: Programming Language :: Python :: 3
Classifier: Topic :: Software Development :: Libraries :: Python Modules
Requires-Dist: infi.pyutils
Requires-Dist: munch
Requires-Dist: pyvmomi
Requires-Dist: setuptools
Requires-Dist: six
